MANIFEST.in
README.md
setup.cfg
setup.py
lingwa_demo/__init__.py
lingwa_demo/main.py
lingwa_demo/tt1.md
lingwa_demo/tt2.js
lingwa_demo.egg-info/PKG-INFO
lingwa_demo.egg-info/SOURCES.txt
lingwa_demo.egg-info/dependency_links.txt
lingwa_demo.egg-info/top_level.txt