Metadata-Version: 2.1
Name: lingwa-demo
Version: 2019.3.31
Summary: A demo for python packaging.
Home-page: https://github.com/pypa/sampleproject
Author: LingWang
Author-email: lingwang@wcysite.com
License: MIT
Project-URL: Bug Tracker, https://github.com/pypa/sampleproject/issues
Keywords: demo
Platform: UNKNOWN
Classifier: Programming Language :: Python :: 3
Classifier: License :: OSI Approved :: MIT License
Classifier: Operating System :: OS Independent
Requires-Python: >=3.6
